conesearch_alchemy/__init__.py
conesearch_alchemy/math.py
conesearch_alchemy/point.py
conesearch_alchemy/util.py
conesearch_alchemy-1.1.0.dist-info/LICENSE
conesearch_alchemy-1.1.0.dist-info/METADATA
conesearch_alchemy-1.1.0.dist-info/WHEEL
conesearch_alchemy-1.1.0.dist-info/RECORD
