Metadata-Version: 2.1
Name: conesearch-alchemy
Version: 1.1.0
Summary: SQLAlchemy extension for indexed cone searches in astronomical catalogs
Home-page: https://github.com/skyportal/conesearch-alchemy
License: BSD-3-Clause
Author: Leo Singer
Author-email: leo.singer@ligo.org
Requires-Python: >=3.10,<4.0
Classifier: Development Status :: 5 - Production/Stable
Classifier: License :: OSI Approved :: BSD License
Classifier: Programming Language :: Python :: 3
Classifier: Programming Language :: Python :: 3.10
Classifier: Programming Language :: Python :: 3.11
Classifier: Programming Language :: Python :: 3.12
Classifier: Topic :: Database
Classifier: Topic :: Scientific/Engineering :: Astronomy
Requires-Dist: pytest-cov (>=5.0.0,<6.0.0)
Requires-Dist: sqlalchemy
Project-URL: Repository, https://github.com/skyportal/conesearch-alchemy
